{
  "Accommodation": [
    {
      "id": 10062294,
      "category": "Accommodation",
      "final_score": 0.6032004472778708
    },
    {
      "id": 10058007,
      "category": "Accommodation",
      "final_score": 0.5706900236175925
    },
    {
      "id": 10064399,
      "category": "Accommodation",
      "final_score": 0.5659184963062306
    },
    {
      "id": 10042948,
      "category": "Accommodation",
      "final_score": 0.5575834725795417
    },
    {
      "id": 10042945,
      "category": "Accommodation",
      "final_score": 0.5574020518415886
    },
    {
      "id": 10044793,
      "category": "Accommodation",
      "final_score": 0.5567700973649233
    },
    {
      "id": 1000108328,
      "category": "Accommodation",
      "final_score": 0.5556144983502928
    },
    {
      "id": 1000068,
      "category": "Accommodation",
      "final_score": 0.5545546633725568
    },
    {
      "id": 10062985,
      "category": "Accommodation",
      "final_score": 0.5454958263976702
    },
    {
      "id": 10064532,
      "category": "Accommodation",
      "final_score": 0.5436433270849237
    },
    {
      "id": 10065096,
      "category": "Accommodation",
      "final_score": 0.5392061844743737
    },
    {
      "id": 10051273,
      "category": "Accommodation",
      "final_score": 0.5389053793211812
    },
    {
      "id": 10063952,
      "category": "Accommodation",
      "final_score": 0.5375598347407539
    },
    {
      "id": 1000113292,
      "category": "Accommodation",
      "final_score": 0.5355535063533414
    },
    {
      "id": 10057347,
      "category": "Accommodation",
      "final_score": 0.5343274218836246
    },
    {
      "id": 10053607,
      "category": "Accommodation",
      "final_score": 0.5323167906658336
    },
    {
      "id": 1000101679,
      "category": "Accommodation",
      "final_score": 0.5311724720297719
    },
    {
      "id": 10057059,
      "category": "Accommodation",
      "final_score": 0.5256718216710027
    },
    {
      "id": 1000088974,
      "category": "Accommodation",
      "final_score": 0.5252262823828717
    },
    {
      "id": 1000109710,
      "category": "Accommodation",
      "final_score": 0.5235806751560855
    },
    {
      "id": 10058524,
      "category": "Accommodation",
      "final_score": 0.5228876465339187
    },
    {
      "id": 3013122,
      "category": "Accommodation",
      "final_score": 0.5222119998498341
    },
    {
      "id": 10059423,
      "category": "Accommodation",
      "final_score": 0.5220894754145755
    },
    {
      "id": 10064996,
      "category": "Accommodation",
      "final_score": 0.5217350560536961
    },
    {
      "id": 3013409,
      "category": "Accommodation",
      "final_score": 0.5211362659218792
    },
    {
      "id": 3013358,
      "category": "Accommodation",
      "final_score": 0.5197255552218045
    },
    {
      "id": 10065235,
      "category": "Accommodation",
      "final_score": 0.5196765062378317
    },
    {
      "id": 10064533,
      "category": "Accommodation",
      "final_score": 0.519151579489252
    },
    {
      "id": 10060859,
      "category": "Accommodation",
      "final_score": 0.5184334214993007
    },
    {
      "id": 10062730,
      "category": "Accommodation",
      "final_score": 0.5160079395991524
    },
    {
      "id": 1000111789,
      "category": "Accommodation",
      "final_score": 0.5150640495271018
    },
    {
      "id": 10062033,
      "category": "Accommodation",
      "final_score": 0.5148124528372208
    },
    {
      "id": 10052291,
      "category": "Accommodation",
      "final_score": 0.5119595340390414
    },
    {
      "id": 10041484,
      "category": "Accommodation",
      "final_score": 0.5114666894353875
    },
    {
      "id": 3011533,
      "category": "Accommodation",
      "final_score": 0.5092329553908377
    },
    {
      "id": 10057249,
      "category": "Accommodation",
      "final_score": 0.5090857038508245
    },
    {
      "id": 3006291,
      "category": "Accommodation",
      "final_score": 0.5090227206217912
    },
    {
      "id": 10044330,
      "category": "Accommodation",
      "final_score": 0.5086394564132708
    },
    {
      "id": 1000113319,
      "category": "Accommodation",
      "final_score": 0.508030174473804
    },
    {
      "id": 10057607,
      "category": "Accommodation",
      "final_score": 0.5073336082807164
    },
    {
      "id": 1000174,
      "category": "Accommodation",
      "final_score": 0.507280558705901
    },
    {
      "id": 10040005,
      "category": "Accommodation",
      "final_score": 0.5071664760123082
    },
    {
      "id": 10046444,
      "category": "Accommodation",
      "final_score": 0.5068662024495303
    },
    {
      "id": 10048892,
      "category": "Accommodation",
      "final_score": 0.5060886875070582
    },
    {
      "id": 10060856,
      "category": "Accommodation",
      "final_score": 0.5051683977521906
    },
    {
      "id": 10055367,
      "category": "Accommodation",
      "final_score": 0.504581568263169
    },
    {
      "id": 1000110878,
      "category": "Accommodation",
      "final_score": 0.5040390232518543
    },
    {
      "id": 3010596,
      "category": "Accommodation",
      "final_score": 0.5031712015500444
    },
    {
      "id": 10048806,
      "category": "Accommodation",
      "final_score": 0.5017909518380373
    },
    {
      "id": 10064208,
      "category": "Accommodation",
      "final_score": 0.4994196093302925
    },
    {
      "id": 10061608,
      "category": "Accommodation",
      "final_score": 0.49909942509948807
    },
    {
      "id": 10048841,
      "category": "Accommodation",
      "final_score": 0.4954794702574239
    },
    {
      "id": 10055839,
      "category": "Accommodation",
      "final_score": 0.49492093296512657
    },
    {
      "id": 1000108403,
      "category": "Accommodation",
      "final_score": 0.49433503398178413
    },
    {
      "id": 3011627,
      "category": "Accommodation",
      "final_score": 0.49408937943390546
    },
    {
      "id": 10044474,
      "category": "Accommodation",
      "final_score": 0.49373884269569673
    },
    {
      "id": 10048410,
      "category": "Accommodation",
      "final_score": 0.49302794905170494
    },
    {
      "id": 3012455,
      "category": "Accommodation",
      "final_score": 0.4926321986404568
    },
    {
      "id": 10060854,
      "category": "Accommodation",
      "final_score": 0.49198736312210156
    },
    {
      "id": 3012759,
      "category": "Accommodation",
      "final_score": 0.4919765342671722
    },
    {
      "id": 10052466,
      "category": "Accommodation",
      "final_score": 0.4919193220579544
    },
    {
      "id": 3002581,
      "category": "Accommodation",
      "final_score": 0.4916414211272062
    },
    {
      "id": 10052560,
      "category": "Accommodation",
      "final_score": 0.4914140278431713
    },
    {
      "id": 10048021,
      "category": "Accommodation",
      "final_score": 0.4909951233901362
    },
    {
      "id": 1000105674,
      "category": "Accommodation",
      "final_score": 0.4906677983479813
    },
    {
      "id": 1000102447,
      "category": "Accommodation",
      "final_score": 0.4895447056828633
    },
    {
      "id": 10061720,
      "category": "Accommodation",
      "final_score": 0.4871806937566379
    },
    {
      "id": 10061610,
      "category": "Accommodation",
      "final_score": 0.486246034680707
    },
    {
      "id": 3017347,
      "category": "Accommodation",
      "final_score": 0.4861265201917586
    },
    {
      "id": 10058804,
      "category": "Accommodation",
      "final_score": 0.4860606609408935
    },
    {
      "id": 10058459,
      "category": "Accommodation",
      "final_score": 0.48594196562408604
    },
    {
      "id": 3000446,
      "category": "Accommodation",
      "final_score": 0.48543232279187903
    },
    {
      "id": 10064958,
      "category": "Accommodation",
      "final_score": 0.4845760222629922
    },
    {
      "id": 10046839,
      "category": "Accommodation",
      "final_score": 0.4838792192999899
    },
    {
      "id": 10061060,
      "category": "Accommodation",
      "final_score": 0.48298954643024694
    },
    {
      "id": 3001945,
      "category": "Accommodation",
      "final_score": 0.48261465117631086
    },
    {
      "id": 3014664,
      "category": "Accommodation",
      "final_score": 0.4823719067151354
    },
    {
      "id": 3005708,
      "category": "Accommodation",
      "final_score": 0.4812162637159893
    },
    {
      "id": 10060408,
      "category": "Accommodation",
      "final_score": 0.480205835429574
    },
    {
      "id": 10044704,
      "category": "Accommodation",
      "final_score": 0.48011353055073114
    },
    {
      "id": 10054601,
      "category": "Accommodation",
      "final_score": 0.4796242887112438
    },
    {
      "id": 3014465,
      "category": "Accommodation",
      "final_score": 0.47911994752462567
    },
    {
      "id": 100098,
      "category": "Accommodation",
      "final_score": 0.4781704074909543
    },
    {
      "id": 1000103570,
      "category": "Accommodation",
      "final_score": 0.4781247435010362
    },
    {
      "id": 10055818,
      "category": "Accommodation",
      "final_score": 0.4776923234260589
    },
    {
      "id": 10060839,
      "category": "Accommodation",
      "final_score": 0.47690580071121247
    },
    {
      "id": 10040659,
      "category": "Accommodation",
      "final_score": 0.4764388370944524
    },
    {
      "id": 10064935,
      "category": "Accommodation",
      "final_score": 0.476319685897572
    },
    {
      "id": 10052935,
      "category": "Accommodation",
      "final_score": 0.4757618678057114
    },
    {
      "id": 10060193,
      "category": "Accommodation",
      "final_score": 0.4752951771572132
    },
    {
      "id": 10052188,
      "category": "Accommodation",
      "final_score": 0.47515243842628985
    },
    {
      "id": 1000109381,
      "category": "Accommodation",
      "final_score": 0.47501161638229483
    },
    {
      "id": 10063317,
      "category": "Accommodation",
      "final_score": 0.4748884910675823
    },
    {
      "id": 10063201,
      "category": "Accommodation",
      "final_score": 0.4745401396562563
    },
    {
      "id": 10059422,
      "category": "Accommodation",
      "final_score": 0.47431120085506456
    },
    {
      "id": 10044471,
      "category": "Accommodation",
      "final_score": 0.47384925189457605
    },
    {
      "id": 3013312,
      "category": "Accommodation",
      "final_score": 0.47375837025760037
    },
    {
      "id": 10063965,
      "category": "Accommodation",
      "final_score": 0.47312877437623596
    },
    {
      "id": 10044360,
      "category": "Accommodation",
      "final_score": 0.47280416441287376
    },
    {
      "id": 10055844,
      "category": "Accommodation",
      "final_score": 0.4722711915108501
    },
    {
      "id": 10057625,
      "category": "Accommodation",
      "final_score": 0.472074451816218
    },
    {
      "id": 10040426,
      "category": "Accommodation",
      "final_score": 0.47160087079105584
    },
    {
      "id": 10060678,
      "category": "Accommodation",
      "final_score": 0.47072940728486523
    },
    {
      "id": 3014625,
      "category": "Accommodation",
      "final_score": 0.470309061630202
    },
    {
      "id": 10045740,
      "category": "Accommodation",
      "final_score": 0.47029942605777875
    },
    {
      "id": 3017234,
      "category": "Accommodation",
      "final_score": 0.4694000995570042
    },
    {
      "id": 10065274,
      "category": "Accommodation",
      "final_score": 0.46934322214229796
    },
    {
      "id": 1000110490,
      "category": "Accommodation",
      "final_score": 0.46800719668222907
    },
    {
      "id": 3005035,
      "category": "Accommodation",
      "final_score": 0.4673368419697163
    },
    {
      "id": 1000111929,
      "category": "Accommodation",
      "final_score": 0.4672950595829813
    },
    {
      "id": 10061844,
      "category": "Accommodation",
      "final_score": 0.4671847844161633
    },
    {
      "id": 10061981,
      "category": "Accommodation",
      "final_score": 0.46668846162929634
    },
    {
      "id": 10055697,
      "category": "Accommodation",
      "final_score": 0.46552698450991054
    },
    {
      "id": 3001494,
      "category": "Accommodation",
      "final_score": 0.46538586389398184
    },
    {
      "id": 10041249,
      "category": "Accommodation",
      "final_score": 0.465345238165304
    },
    {
      "id": 1018974,
      "category": "Accommodation",
      "final_score": 0.46489359394162344
    },
    {
      "id": 1000103201,
      "category": "Accommodation",
      "final_score": 0.464585994536461
    },
    {
      "id": 10059323,
      "category": "Accommodation",
      "final_score": 0.46373178184366276
    },
    {
      "id": 10042423,
      "category": "Accommodation",
      "final_score": 0.463660530772456
    },
    {
      "id": 1000090928,
      "category": "Accommodation",
      "final_score": 0.4632492754741805
    },
    {
      "id": 10059249,
      "category": "Accommodation",
      "final_score": 0.4629535304157277
    },
    {
      "id": 3006187,
      "category": "Accommodation",
      "final_score": 0.4621937613554775
    },
    {
      "id": 1000111438,
      "category": "Accommodation",
      "final_score": 0.46212889105132055
    },
    {
      "id": 1000106256,
      "category": "Accommodation",
      "final_score": 0.46084924530175336
    },
    {
      "id": 1000110189,
      "category": "Accommodation",
      "final_score": 0.46003012244008745
    },
    {
      "id": 10055877,
      "category": "Accommodation",
      "final_score": 0.459703129248467
    },
    {
      "id": 1000110022,
      "category": "Accommodation",
      "final_score": 0.4594712233763893
    },
    {
      "id": 3012133,
      "category": "Accommodation",
      "final_score": 0.45911453966079196
    },
    {
      "id": 3013530,
      "category": "Accommodation",
      "final_score": 0.45871144225021765
    },
    {
      "id": 3003420,
      "category": "Accommodation",
      "final_score": 0.4576519358222379
    },
    {
      "id": 10047942,
      "category": "Accommodation",
      "final_score": 0.4574736022817809
    },
    {
      "id": 3006274,
      "category": "Accommodation",
      "final_score": 0.45705100499228246
    },
    {
      "id": 10062156,
      "category": "Accommodation",
      "final_score": 0.45699931326835747
    },
    {
      "id": 3003569,
      "category": "Accommodation",
      "final_score": 0.45682289902852175
    },
    {
      "id": 1000103605,
      "category": "Accommodation",
      "final_score": 0.4553703257233053
    },
    {
      "id": 10060724,
      "category": "Accommodation",
      "final_score": 0.4549515890406353
    },
    {
      "id": 3013639,
      "category": "Accommodation",
      "final_score": 0.45476842776067444
    },
    {
      "id": 10045710,
      "category": "Accommodation",
      "final_score": 0.4545624866798929
    },
    {
      "id": 10062031,
      "category": "Accommodation",
      "final_score": 0.45425718644461094
    },
    {
      "id": 1000113746,
      "category": "Accommodation",
      "final_score": 0.4539689068519988
    },
    {
      "id": 10043752,
      "category": "Accommodation",
      "final_score": 0.4539334312538432
    },
    {
      "id": 3014394,
      "category": "Accommodation",
      "final_score": 0.4537142905123123
    },
    {
      "id": 10056273,
      "category": "Accommodation",
      "final_score": 0.45335363509475785
    },
    {
      "id": 10063474,
      "category": "Accommodation",
      "final_score": 0.45254817132593933
    },
    {
      "id": 10064482,
      "category": "Accommodation",
      "final_score": 0.4516167635056316
    },
    {
      "id": 10055694,
      "category": "Accommodation",
      "final_score": 0.4511158976108399
    },
    {
      "id": 10064591,
      "category": "Accommodation",
      "final_score": 0.45065638726501656
    },
    {
      "id": 3004935,
      "category": "Accommodation",
      "final_score": 0.4497602087031758
    },
    {
      "id": 10063616,
      "category": "Accommodation",
      "final_score": 0.44905488007934535
    },
    {
      "id": 10058071,
      "category": "Accommodation",
      "final_score": 0.44858792187988356
    }
  ],
  "Cafe": [
    {
      "id": 1651019497,
      "category": "Cafe",
      "final_score": 0.4962130295187819
    },
    {
      "id": 1426647455,
      "category": "Cafe",
      "final_score": 0.4920488897604245
    },
    {
      "id": 1331157860,
      "category": "Cafe",
      "final_score": 0.4669298536452263
    },
    {
      "id": 2012122325,
      "category": "Cafe",
      "final_score": 0.4607604751173133
    },
    {
      "id": 1876301121,
      "category": "Cafe",
      "final_score": 0.46002448415831304
    },
    {
      "id": 1001417136,
      "category": "Cafe",
      "final_score": 0.45482726772390863
    },
    {
      "id": 1605447318,
      "category": "Cafe",
      "final_score": 0.45035527122306446
    },
    {
      "id": 2017141901,
      "category": "Cafe",
      "final_score": 0.44553466733732294
    },
    {
      "id": 1086491623,
      "category": "Cafe",
      "final_score": 0.44427439116707046
    },
    {
      "id": 2089930981,
      "category": "Cafe",
      "final_score": 0.4409865064203973
    },
    {
      "id": 2067021446,
      "category": "Cafe",
      "final_score": 0.4398561629624598
    },
    {
      "id": 1024529564,
      "category": "Cafe",
      "final_score": 0.4376061045421257
    },
    {
      "id": 1266299794,
      "category": "Cafe",
      "final_score": 0.4311963502486469
    },
    {
      "id": 1606960077,
      "category": "Cafe",
      "final_score": 0.42726917175020196
    },
    {
      "id": 2067971861,
      "category": "Cafe",
      "final_score": 0.42403308161524617
    },
    {
      "id": 1215792352,
      "category": "Cafe",
      "final_score": 0.42319375869424025
    },
    {
      "id": 1761686436,
      "category": "Cafe",
      "final_score": 0.42266178910905255
    },
    {
      "id": 1647063521,
      "category": "Cafe",
      "final_score": 0.4221982303268386
    },
    {
      "id": 1867724165,
      "category": "Cafe",
      "final_score": 0.4207492349392764
    },
    {
      "id": 1026225860,
      "category": "Cafe",
      "final_score": 0.42012723679394876
    },
    {
      "id": 1623800311,
      "category": "Cafe",
      "final_score": 0.41733490989550315
    },
    {
      "id": 1009179914,
      "category": "Cafe",
      "final_score": 0.4170991450393987
    },
    {
      "id": 1292591709,
      "category": "Cafe",
      "final_score": 0.4167304159220775
    },
    {
      "id": 1273489865,
      "category": "Cafe",
      "final_score": 0.41476424087637537
    },
    {
      "id": 1275789425,
      "category": "Cafe",
      "final_score": 0.41336841856508805
    },
    {
      "id": 1869523471,
      "category": "Cafe",
      "final_score": 0.4115054517468207
    },
    {
      "id": 1133303813,
      "category": "Cafe",
      "final_score": 0.40751815141138686
    },
    {
      "id": 1195768568,
      "category": "Cafe",
      "final_score": 0.40632468054883375
    },
    {
      "id": 1547896837,
      "category": "Cafe",
      "final_score": 0.40313689852364826
    },
    {
      "id": 2013389102,
      "category": "Cafe",
      "final_score": 0.40266972668201734
    },
    {
      "id": 1824086717,
      "category": "Cafe",
      "final_score": 0.4011286733913867
    },
    {
      "id": 1974801379,
      "category": "Cafe",
      "final_score": 0.4009879504171015
    },
    {
      "id": 1659347323,
      "category": "Cafe",
      "final_score": 0.40077928772484755
    },
    {
      "id": 1588834856,
      "category": "Cafe",
      "final_score": 0.40038778086323396
    },
    {
      "id": 1056262384,
      "category": "Cafe",
      "final_score": 0.3995611315865693
    },
    {
      "id": 15373350,
      "category": "Cafe",
      "final_score": 0.3987961468984763
    },
    {
      "id": 1081008717,
      "category": "Cafe",
      "final_score": 0.3983301455125267
    },
    {
      "id": 1087262116,
      "category": "Cafe",
      "final_score": 0.3970723100052202
    },
    {
      "id": 1682187275,
      "category": "Cafe",
      "final_score": 0.3954332324083289
    },
    {
      "id": 35256483,
      "category": "Cafe",
      "final_score": 0.3954154894969651
    },
    {
      "id": 1612034459,
      "category": "Cafe",
      "final_score": 0.3939031463005331
    },
    {
      "id": 1013733901,
      "category": "Cafe",
      "final_score": 0.39328803527012857
    },
    {
      "id": 1569323095,
      "category": "Cafe",
      "final_score": 0.3929165828541133
    },
    {
      "id": 1500318606,
      "category": "Cafe",
      "final_score": 0.3918996555517812
    },
    {
      "id": 1442771903,
      "category": "Cafe",
      "final_score": 0.38598243052334175
    },
    {
      "id": 1899236965,
      "category": "Cafe",
      "final_score": 0.3852740994615394
    },
    {
      "id": 2038520626,
      "category": "Cafe",
      "final_score": 0.38497017748878787
    },
    {
      "id": 1013606867,
      "category": "Cafe",
      "final_score": 0.3842445689847506
    },
    {
      "id": 1517734190,
      "category": "Cafe",
      "final_score": 0.3841055903803962
    },
    {
      "id": 1019654977,
      "category": "Cafe",
      "final_score": 0.38260817794383756
    },
    {
      "id": 1526759655,
      "category": "Cafe",
      "final_score": 0.3821421505781524
    },
    {
      "id": 1506869074,
      "category": "Cafe",
      "final_score": 0.3810295613737499
    },
    {
      "id": 1671795817,
      "category": "Cafe",
      "final_score": 0.378743659239143
    },
    {
      "id": 2058022471,
      "category": "Cafe",
      "final_score": 0.37795588652310763
    },
    {
      "id": 34203501,
      "category": "Cafe",
      "final_score": 0.3766962512163765
    },
    {
      "id": 1756159133,
      "category": "Cafe",
      "final_score": 0.3753328597351068
    },
    {
      "id": 2003320621,
      "category": "Cafe",
      "final_score": 0.3738379289982888
    },
    {
      "id": 1174448798,
      "category": "Cafe",
      "final_score": 0.3735040245576715
    },
    {
      "id": 1033478410,
      "category": "Cafe",
      "final_score": 0.37319252585683055
    },
    {
      "id": 1752487744,
      "category": "Cafe",
      "final_score": 0.37300705969913855
    },
    {
      "id": 1927406130,
      "category": "Cafe",
      "final_score": 0.3721029327576634
    },
    {
      "id": 263503029,
      "category": "Cafe",
      "final_score": 0.3711806855468438
    },
    {
      "id": 1426989487,
      "category": "Cafe",
      "final_score": 0.37083357574283604
    },
    {
      "id": 2051244903,
      "category": "Cafe",
      "final_score": 0.370367906788754
    },
    {
      "id": 1536161656,
      "category": "Cafe",
      "final_score": 0.37016900615826087
    },
    {
      "id": 1709924447,
      "category": "Cafe",
      "final_score": 0.3695696064494776
    },
    {
      "id": 1338491802,
      "category": "Cafe",
      "final_score": 0.3691030632708872
    },
    {
      "id": 1391511090,
      "category": "Cafe",
      "final_score": 0.3690641666214854
    },
    {
      "id": 1442187201,
      "category": "Cafe",
      "final_score": 0.36843033353571125
    },
    {
      "id": 1220981140,
      "category": "Cafe",
      "final_score": 0.36816587463324063
    },
    {
      "id": 1289622019,
      "category": "Cafe",
      "final_score": 0.36663328907799697
    },
    {
      "id": 1104085754,
      "category": "Cafe",
      "final_score": 0.365826783934706
    },
    {
      "id": 1839133695,
      "category": "Cafe",
      "final_score": 0.3636698549126915
    },
    {
      "id": 1495937611,
      "category": "Cafe",
      "final_score": 0.36230911680351907
    },
    {
      "id": 1111813353,
      "category": "Cafe",
      "final_score": 0.3602177880509065
    },
    {
      "id": 1209837360,
      "category": "Cafe",
      "final_score": 0.3597616990848261
    },
    {
      "id": 1891894301,
      "category": "Cafe",
      "final_score": 0.3588446661385643
    },
    {
      "id": 1621771668,
      "category": "Cafe",
      "final_score": 0.35721799386464864
    },
    {
      "id": 1299462841,
      "category": "Cafe",
      "final_score": 0.35632435169612453
    },
    {
      "id": 36399670,
      "category": "Cafe",
      "final_score": 0.35621198486830113
    },
    {
      "id": 1504291324,
      "category": "Cafe",
      "final_score": 0.3542074785072308
    },
    {
      "id": 1249217189,
      "category": "Cafe",
      "final_score": 0.35398172363737257
    },
    {
      "id": 1046848158,
      "category": "Cafe",
      "final_score": 0.35173507039016805
    },
    {
      "id": 1070351925,
      "category": "Cafe",
      "final_score": 0.3501492352208687
    },
    {
      "id": 1962975056,
      "category": "Cafe",
      "final_score": 0.3483840110796831
    },
    {
      "id": 1288938606,
      "category": "Cafe",
      "final_score": 0.34618062977626285
    },
    {
      "id": 2069032826,
      "category": "Cafe",
      "final_score": 0.3437429437931159
    },
    {
      "id": 38520417,
      "category": "Cafe",
      "final_score": 0.34353507379757237
    },
    {
      "id": 1083326838,
      "category": "Cafe",
      "final_score": 0.3427579725363571
    },
    {
      "id": 19861939,
      "category": "Cafe",
      "final_score": 0.3426745357810749
    },
    {
      "id": 2064259008,
      "category": "Cafe",
      "final_score": 0.3426239081281927
    },
    {
      "id": 1836092492,
      "category": "Cafe",
      "final_score": 0.34214574807359566
    },
    {
      "id": 2031533892,
      "category": "Cafe",
      "final_score": 0.3419333846499649
    },
    {
      "id": 1106082140,
      "category": "Cafe",
      "final_score": 0.34078275613993825
    },
    {
      "id": 1926050460,
      "category": "Cafe",
      "final_score": 0.34022627691862944
    },
    {
      "id": 1263529731,
      "category": "Cafe",
      "final_score": 0.3392038729871456
    },
    {
      "id": 1439249340,
      "category": "Cafe",
      "final_score": 0.3386251459355945
    },
    {
      "id": 34537489,
      "category": "Cafe",
      "final_score": 0.33676368735041406
    },
    {
      "id": 1879279368,
      "category": "Cafe",
      "final_score": 0.33673120230242976
    },
    {
      "id": 1219942297,
      "category": "Cafe",
      "final_score": 0.3363052196420275
    },
    {
      "id": 2078030409,
      "category": "Cafe",
      "final_score": 0.3360858658698345
    },
    {
      "id": 1758181058,
      "category": "Cafe",
      "final_score": 0.33510124302167255
    },
    {
      "id": 19900143,
      "category": "Cafe",
      "final_score": 0.33394662231116007
    },
    {
      "id": 1994587010,
      "category": "Cafe",
      "final_score": 0.33386069593848877
    },
    {
      "id": 1721611016,
      "category": "Cafe",
      "final_score": 0.3328411108236121
    },
    {
      "id": 79408101,
      "category": "Cafe",
      "final_score": 0.3319850525147604
    },
    {
      "id": 1921017062,
      "category": "Cafe",
      "final_score": 0.33069210072443467
    },
    {
      "id": 1546169801,
      "category": "Cafe",
      "final_score": 0.3301419910360668
    },
    {
      "id": 2017317134,
      "category": "Cafe",
      "final_score": 0.3292933726823867
    },
    {
      "id": 1779443730,
      "category": "Cafe",
      "final_score": 0.32863577147538026
    },
    {
      "id": 1926085994,
      "category": "Cafe",
      "final_score": 0.3260438924397771
    },
    {
      "id": 1683765421,
      "category": "Cafe",
      "final_score": 0.3246396645988128
    },
    {
      "id": 2094977764,
      "category": "Cafe",
      "final_score": 0.32332183667123976
    },
    {
      "id": 1459760339,
      "category": "Cafe",
      "final_score": 0.3232898724459881
    },
    {
      "id": 1099817979,
      "category": "Cafe",
      "final_score": 0.32301050074509685
    },
    {
      "id": 1270153623,
      "category": "Cafe",
      "final_score": 0.32300087570867014
    },
    {
      "id": 1149019688,
      "category": "Cafe",
      "final_score": 0.32263360325479024
    },
    {
      "id": 1843451871,
      "category": "Cafe",
      "final_score": 0.32062826780060955
    },
    {
      "id": 1656009767,
      "category": "Cafe",
      "final_score": 0.32055561888695944
    },
    {
      "id": 30959782,
      "category": "Cafe",
      "final_score": 0.32019028900327795
    },
    {
      "id": 15702445,
      "category": "Cafe",
      "final_score": 0.3193883480875038
    },
    {
      "id": 1933690279,
      "category": "Cafe",
      "final_score": 0.3191803789964687
    },
    {
      "id": 1169844332,
      "category": "Cafe",
      "final_score": 0.31854426680054393
    },
    {
      "id": 1265990790,
      "category": "Cafe",
      "final_score": 0.3181071841407132
    },
    {
      "id": 13320528,
      "category": "Cafe",
      "final_score": 0.3181006625859511
    },
    {
      "id": 38345396,
      "category": "Cafe",
      "final_score": 0.318044432871004
    },
    {
      "id": 1325516945,
      "category": "Cafe",
      "final_score": 0.31778533688776733
    },
    {
      "id": 1497289783,
      "category": "Cafe",
      "final_score": 0.31672300054815367
    },
    {
      "id": 38274668,
      "category": "Cafe",
      "final_score": 0.3161353406503073
    },
    {
      "id": 1277825412,
      "category": "Cafe",
      "final_score": 0.3145925878329599
    },
    {
      "id": 1176434004,
      "category": "Cafe",
      "final_score": 0.3137088385725607
    },
    {
      "id": 15299378,
      "category": "Cafe",
      "final_score": 0.3124417306423959
    },
    {
      "id": 1578033962,
      "category": "Cafe",
      "final_score": 0.3111334239447985
    },
    {
      "id": 1777557364,
      "category": "Cafe",
      "final_score": 0.3102540094805618
    },
    {
      "id": 1612246511,
      "category": "Cafe",
      "final_score": 0.3089305122141606
    },
    {
      "id": 1557387521,
      "category": "Cafe",
      "final_score": 0.3086835964833202
    },
    {
      "id": 15294021,
      "category": "Cafe",
      "final_score": 0.3079329785330598
    },
    {
      "id": 1315387703,
      "category": "Cafe",
      "final_score": 0.3071400016204484
    },
    {
      "id": 2091156925,
      "category": "Cafe",
      "final_score": 0.3066386894950042
    },
    {
      "id": 1733358179,
      "category": "Cafe",
      "final_score": 0.3062535004886791
    },
    {
      "id": 1212033877,
      "category": "Cafe",
      "final_score": 0.3060751028696541
    },
    {
      "id": 1267158607,
      "category": "Cafe",
      "final_score": 0.3037192906094382
    },
    {
      "id": 1457952472,
      "category": "Cafe",
      "final_score": 0.3034221673017143
    },
    {
      "id": 1750727150,
      "category": "Cafe",
      "final_score": 0.3031636017752684
    },
    {
      "id": 11887822,
      "category": "Cafe",
      "final_score": 0.301787454843099
    },
    {
      "id": 1697573959,
      "category": "Cafe",
      "final_score": 0.3016785487415975
    },
    {
      "id": 1900553385,
      "category": "Cafe",
      "final_score": 0.30106289931639196
    },
    {
      "id": 1689574654,
      "category": "Cafe",
      "final_score": 0.2995803533927008
    },
    {
      "id": 20585367,
      "category": "Cafe",
      "final_score": 0.29873620227802006
    },
    {
      "id": 1639218638,
      "category": "Cafe",
      "final_score": 0.29834618333671686
    }
  ],
  "Restaurant": [
    {
      "id": 11824654,
      "category": "Restaurant",
      "final_score": 0.503935528666871
    },
    {
      "id": 1229100783,
      "category": "Restaurant",
      "final_score": 0.4886036181836495
    },
    {
      "id": 1175159881,
      "category": "Restaurant",
      "final_score": 0.486377699998457
    },
    {
      "id": 1567062059,
      "category": "Restaurant",
      "final_score": 0.4858721015953403
    },
    {
      "id": 1333300547,
      "category": "Restaurant",
      "final_score": 0.4802784899847389
    },
    {
      "id": 1154907883,
      "category": "Restaurant",
      "final_score": 0.47944342310309085
    },
    {
      "id": 1216081294,
      "category": "Restaurant",
      "final_score": 0.4788596054793341
    },
    {
      "id": 15380143,
      "category": "Restaurant",
      "final_score": 0.4772101453565823
    },
    {
      "id": 32038666,
      "category": "Restaurant",
      "final_score": 0.4756135219957676
    },
    {
      "id": 1017827824,
      "category": "Restaurant",
      "final_score": 0.474971977181399
    },
    {
      "id": 1417252039,
      "category": "Restaurant",
      "final_score": 0.4697208638563311
    },
    {
      "id": 1368387404,
      "category": "Restaurant",
      "final_score": 0.46690934104160015
    },
    {
      "id": 38215574,
      "category": "Restaurant",
      "final_score": 0.466396998971496
    },
    {
      "id": 1681518999,
      "category": "Restaurant",
      "final_score": 0.4659519184879952
    },
    {
      "id": 1947256113,
      "category": "Restaurant",
      "final_score": 0.4607487377835436
    },
    {
      "id": 945583235,
      "category": "Restaurant",
      "final_score": 0.4593298345097669
    },
    {
      "id": 1704605277,
      "category": "Restaurant",
      "final_score": 0.457011940439434
    },
    {
      "id": 36258263,
      "category": "Restaurant",
      "final_score": 0.45619449802809603
    },
    {
      "id": 1890343764,
      "category": "Restaurant",
      "final_score": 0.4548388674761927
    },
    {
      "id": 1346405445,
      "category": "Restaurant",
      "final_score": 0.45239791244238814
    },
    {
      "id": 1131502371,
      "category": "Restaurant",
      "final_score": 0.452141925520748
    },
    {
      "id": 1360913554,
      "category": "Restaurant",
      "final_score": 0.45087213177093494
    },
    {
      "id": 12031474,
      "category": "Restaurant",
      "final_score": 0.44998974934623776
    },
    {
      "id": 1015624214,
      "category": "Restaurant",
      "final_score": 0.44991855008020326
    },
    {
      "id": 12951301,
      "category": "Restaurant",
      "final_score": 0.4486704371440038
    },
    {
      "id": 1380888385,
      "category": "Restaurant",
      "final_score": 0.44860177001482954
    },
    {
      "id": 1874304021,
      "category": "Restaurant",
      "final_score": 0.44837672952703334
    },
    {
      "id": 1547280580,
      "category": "Restaurant",
      "final_score": 0.4480524548945991
    },
    {
      "id": 1495747568,
      "category": "Restaurant",
      "final_score": 0.4476886927296462
    },
    {
      "id": 1463670736,
      "category": "Restaurant",
      "final_score": 0.44592135795586546
    },
    {
      "id": 19729238,
      "category": "Restaurant",
      "final_score": 0.4448508871583868
    },
    {
      "id": 15345030,
      "category": "Restaurant",
      "final_score": 0.44484078819750605
    },
    {
      "id": 15291375,
      "category": "Restaurant",
      "final_score": 0.44398815320497365
    },
    {
      "id": 37056132,
      "category": "Restaurant",
      "final_score": 0.44344856575770497
    },
    {
      "id": 15318802,
      "category": "Restaurant",
      "final_score": 0.44242221604729115
    },
    {
      "id": 1497296016,
      "category": "Restaurant",
      "final_score": 0.4418191050674423
    },
    {
      "id": 1029274799,
      "category": "Restaurant",
      "final_score": 0.4417271695395653
    },
    {
      "id": 15315713,
      "category": "Restaurant",
      "final_score": 0.4412511703840072
    },
    {
      "id": 1190849182,
      "category": "Restaurant",
      "final_score": 0.441212540381171
    },
    {
      "id": 1775815561,
      "category": "Restaurant",
      "final_score": 0.44022404602238324
    },
    {
      "id": 15351961,
      "category": "Restaurant",
      "final_score": 0.439284541524846
    },
    {
      "id": 2041829875,
      "category": "Restaurant",
      "final_score": 0.43868293517926743
    },
    {
      "id": 1053416085,
      "category": "Restaurant",
      "final_score": 0.438423292148956
    },
    {
      "id": 436974851,
      "category": "Restaurant",
      "final_score": 0.43827736359363895
    },
    {
      "id": 1604061144,
      "category": "Restaurant",
      "final_score": 0.4382477640477611
    },
    {
      "id": 1302280920,
      "category": "Restaurant",
      "final_score": 0.43742660865957894
    },
    {
      "id": 2048194061,
      "category": "Restaurant",
      "final_score": 0.43630755351525863
    },
    {
      "id": 12780466,
      "category": "Restaurant",
      "final_score": 0.4361433242942795
    },
    {
      "id": 1479747263,
      "category": "Restaurant",
      "final_score": 0.4355839210501317
    },
    {
      "id": 1503837624,
      "category": "Restaurant",
      "final_score": 0.4342451051412306
    },
    {
      "id": 37370900,
      "category": "Restaurant",
      "final_score": 0.43411749566821906
    },
    {
      "id": 2057775610,
      "category": "Restaurant",
      "final_score": 0.43251181778092557
    },
    {
      "id": 1463097899,
      "category": "Restaurant",
      "final_score": 0.4314761385512732
    },
    {
      "id": 1563178271,
      "category": "Restaurant",
      "final_score": 0.43140502182674534
    },
    {
      "id": 1950305815,
      "category": "Restaurant",
      "final_score": 0.431281357563988
    },
    {
      "id": 15302317,
      "category": "Restaurant",
      "final_score": 0.4309145892995078
    },
    {
      "id": 2098103072,
      "category": "Restaurant",
      "final_score": 0.42953691781738307
    },
    {
      "id": 21116582,
      "category": "Restaurant",
      "final_score": 0.428899606740469
    },
    {
      "id": 2075106875,
      "category": "Restaurant",
      "final_score": 0.4286281555341502
    },
    {
      "id": 1671909230,
      "category": "Restaurant",
      "final_score": 0.4286061464170102
    },
    {
      "id": 15315322,
      "category": "Restaurant",
      "final_score": 0.42833358798794274
    },
    {
      "id": 1325291875,
      "category": "Restaurant",
      "final_score": 0.4280596335535918
    },
    {
      "id": 1167311952,
      "category": "Restaurant",
      "final_score": 0.42766245053566554
    },
    {
      "id": 15294097,
      "category": "Restaurant",
      "final_score": 0.42742769058744146
    },
    {
      "id": 1953425523,
      "category": "Restaurant",
      "final_score": 0.4255807654621265
    },
    {
      "id": 36541810,
      "category": "Restaurant",
      "final_score": 0.4255703390321568
    },
    {
      "id": 15322337,
      "category": "Restaurant",
      "final_score": 0.42532394442033405
    },
    {
      "id": 30968979,
      "category": "Restaurant",
      "final_score": 0.42514761976201787
    },
    {
      "id": 1406475436,
      "category": "Restaurant",
      "final_score": 0.4249339663622555
    },
    {
      "id": 15374062,
      "category": "Restaurant",
      "final_score": 0.4247157214079855
    },
    {
      "id": 1307856893,
      "category": "Restaurant",
      "final_score": 0.42462351608421534
    },
    {
      "id": 1841743441,
      "category": "Restaurant",
      "final_score": 0.4236972801929445
    },
    {
      "id": 37668482,
      "category": "Restaurant",
      "final_score": 0.42288404383710293
    },
    {
      "id": 1276604550,
      "category": "Restaurant",
      "final_score": 0.42147476657425204
    },
    {
      "id": 21679370,
      "category": "Restaurant",
      "final_score": 0.42127783158753423
    },
    {
      "id": 1261902989,
      "category": "Restaurant",
      "final_score": 0.42110296526468755
    },
    {
      "id": 1868103084,
      "category": "Restaurant",
      "final_score": 0.4209614005495282
    },
    {
      "id": 1430081795,
      "category": "Restaurant",
      "final_score": 0.42064059261810893
    },
    {
      "id": 1938239395,
      "category": "Restaurant",
      "final_score": 0.42040880017367677
    },
    {
      "id": 1367787468,
      "category": "Restaurant",
      "final_score": 0.42012278317948076
    },
    {
      "id": 1635128478,
      "category": "Restaurant",
      "final_score": 0.4199014886708332
    },
    {
      "id": 1310944050,
      "category": "Restaurant",
      "final_score": 0.41974760965860924
    },
    {
      "id": 1739251514,
      "category": "Restaurant",
      "final_score": 0.4196891783411888
    },
    {
      "id": 33732587,
      "category": "Restaurant",
      "final_score": 0.41946681326044216
    },
    {
      "id": 15376107,
      "category": "Restaurant",
      "final_score": 0.4187412008771943
    },
    {
      "id": 36543472,
      "category": "Restaurant",
      "final_score": 0.41855419394229365
    },
    {
      "id": 1289555795,
      "category": "Restaurant",
      "final_score": 0.41817366465126316
    },
    {
      "id": 1661351403,
      "category": "Restaurant",
      "final_score": 0.4180725263752364
    },
    {
      "id": 1088145777,
      "category": "Restaurant",
      "final_score": 0.41795605449880885
    },
    {
      "id": 1161455816,
      "category": "Restaurant",
      "final_score": 0.4177208621836331
    },
    {
      "id": 12926077,
      "category": "Restaurant",
      "final_score": 0.41685193137564114
    },
    {
      "id": 1140539859,
      "category": "Restaurant",
      "final_score": 0.4168185223373811
    },
    {
      "id": 11626341,
      "category": "Restaurant",
      "final_score": 0.41681221192469786
    },
    {
      "id": 1278298701,
      "category": "Restaurant",
      "final_score": 0.41669044288945645
    },
    {
      "id": 15380240,
      "category": "Restaurant",
      "final_score": 0.4166230188218321
    },
    {
      "id": 1760318925,
      "category": "Restaurant",
      "final_score": 0.4165773748566451
    },
    {
      "id": 2077873969,
      "category": "Restaurant",
      "final_score": 0.41644569603989207
    },
    {
      "id": 1799014321,
      "category": "Restaurant",
      "final_score": 0.4164296830404944
    },
    {
      "id": 1246457673,
      "category": "Restaurant",
      "final_score": 0.4162680260448052
    },
    {
      "id": 15368789,
      "category": "Restaurant",
      "final_score": 0.41543792850351313
    },
    {
      "id": 1846817040,
      "category": "Restaurant",
      "final_score": 0.4144687426465006
    },
    {
      "id": 35664675,
      "category": "Restaurant",
      "final_score": 0.4143826884955596
    },
    {
      "id": 1323935877,
      "category": "Restaurant",
      "final_score": 0.41408872670803415
    },
    {
      "id": 1535120123,
      "category": "Restaurant",
      "final_score": 0.41303673306958877
    },
    {
      "id": 1188604096,
      "category": "Restaurant",
      "final_score": 0.4129011339209943
    },
    {
      "id": 1547353286,
      "category": "Restaurant",
      "final_score": 0.41289106187731067
    },
    {
      "id": 21563187,
      "category": "Restaurant",
      "final_score": 0.4126975059244162
    },
    {
      "id": 15328404,
      "category": "Restaurant",
      "final_score": 0.41212442699664276
    },
    {
      "id": 1520374355,
      "category": "Restaurant",
      "final_score": 0.41165079737145105
    },
    {
      "id": 32185304,
      "category": "Restaurant",
      "final_score": 0.41133042339983755
    },
    {
      "id": 2140078078,
      "category": "Restaurant",
      "final_score": 0.4111358492388937
    },
    {
      "id": 1587239044,
      "category": "Restaurant",
      "final_score": 0.41098639575183227
    },
    {
      "id": 15382768,
      "category": "Restaurant",
      "final_score": 0.4104219643142128
    },
    {
      "id": 1453209507,
      "category": "Restaurant",
      "final_score": 0.41027291834073837
    },
    {
      "id": 1969057580,
      "category": "Restaurant",
      "final_score": 0.4095151702804918
    },
    {
      "id": 1832769863,
      "category": "Restaurant",
      "final_score": 0.40927384125191285
    },
    {
      "id": 1642640928,
      "category": "Restaurant",
      "final_score": 0.4089277912901489
    },
    {
      "id": 15318226,
      "category": "Restaurant",
      "final_score": 0.4084570402518792
    },
    {
      "id": 404484119,
      "category": "Restaurant",
      "final_score": 0.4081494898687478
    },
    {
      "id": 1463664286,
      "category": "Restaurant",
      "final_score": 0.40775522130724934
    },
    {
      "id": 1043586683,
      "category": "Restaurant",
      "final_score": 0.40681461347515174
    },
    {
      "id": 1314819965,
      "category": "Restaurant",
      "final_score": 0.40666799829965444
    },
    {
      "id": 15318709,
      "category": "Restaurant",
      "final_score": 0.406155486808682
    },
    {
      "id": 1888786624,
      "category": "Restaurant",
      "final_score": 0.4058802613987795
    },
    {
      "id": 2096131729,
      "category": "Restaurant",
      "final_score": 0.4054302109653542
    },
    {
      "id": 1430509021,
      "category": "Restaurant",
      "final_score": 0.4053580550690947
    },
    {
      "id": 15344738,
      "category": "Restaurant",
      "final_score": 0.4050992223436764
    },
    {
      "id": 1918083346,
      "category": "Restaurant",
      "final_score": 0.4050403322118003
    },
    {
      "id": 37059478,
      "category": "Restaurant",
      "final_score": 0.4044871427489103
    },
    {
      "id": 1416506512,
      "category": "Restaurant",
      "final_score": 0.40427917580335804
    },
    {
      "id": 1562025223,
      "category": "Restaurant",
      "final_score": 0.40392319215709754
    },
    {
      "id": 15362879,
      "category": "Restaurant",
      "final_score": 0.40380050488157054
    },
    {
      "id": 15372688,
      "category": "Restaurant",
      "final_score": 0.4036171720516148
    },
    {
      "id": 1379005450,
      "category": "Restaurant",
      "final_score": 0.4035416863683994
    },
    {
      "id": 1449236862,
      "category": "Restaurant",
      "final_score": 0.4035352696546512
    },
    {
      "id": 1843519259,
      "category": "Restaurant",
      "final_score": 0.40319225514675394
    },
    {
      "id": 1048928439,
      "category": "Restaurant",
      "final_score": 0.4019426866126531
    },
    {
      "id": 15338997,
      "category": "Restaurant",
      "final_score": 0.4017613438946413
    },
    {
      "id": 1658810393,
      "category": "Restaurant",
      "final_score": 0.401411652768086
    },
    {
      "id": 37191640,
      "category": "Restaurant",
      "final_score": 0.40088616585302267
    },
    {
      "id": 1050598409,
      "category": "Restaurant",
      "final_score": 0.40068699118335016
    },
    {
      "id": 1103963861,
      "category": "Restaurant",
      "final_score": 0.3999204091327808
    },
    {
      "id": 15373850,
      "category": "Restaurant",
      "final_score": 0.39976223611422923
    },
    {
      "id": 1236919265,
      "category": "Restaurant",
      "final_score": 0.3993970103382668
    },
    {
      "id": 1347619457,
      "category": "Restaurant",
      "final_score": 0.39936907703756963
    },
    {
      "id": 939233594,
      "category": "Restaurant",
      "final_score": 0.39916680243244157
    },
    {
      "id": 1274361921,
      "category": "Restaurant",
      "final_score": 0.39851074500776207
    },
    {
      "id": 15369843,
      "category": "Restaurant",
      "final_score": 0.3982651634105526
    },
    {
      "id": 37799505,
      "category": "Restaurant",
      "final_score": 0.39818878974476773
    },
    {
      "id": 1100806567,
      "category": "Restaurant",
      "final_score": 0.39802469249555583
    }
  ],
  "Attraction": [
    {
      "id": 1378194684,
      "category": "Attraction",
      "final_score": 0.48477466884100795
    },
    {
      "id": 11592129,
      "category": "Attraction",
      "final_score": 0.43145953751651306
    },
    {
      "id": 1800696554,
      "category": "Attraction",
      "final_score": 0.41000458196790984
    },
    {
      "id": 1357865119,
      "category": "Attraction",
      "final_score": 0.40373137726078673
    },
    {
      "id": 20107994,
      "category": "Attraction",
      "final_score": 0.3993989505970243
    },
    {
      "id": 13491745,
      "category": "Attraction",
      "final_score": 0.38473617254334547
    },
    {
      "id": 13491906,
      "category": "Attraction",
      "final_score": 0.371046827341309
    },
    {
      "id": 13068554,
      "category": "Attraction",
      "final_score": 0.3696693694827796
    },
    {
      "id": 1848252796,
      "category": "Attraction",
      "final_score": 0.361376087431667
    },
    {
      "id": 1300520912,
      "category": "Attraction",
      "final_score": 0.35924914901420274
    },
    {
      "id": 13491005,
      "category": "Attraction",
      "final_score": 0.3522376477350865
    },
    {
      "id": 1675156043,
      "category": "Attraction",
      "final_score": 0.3468549575157465
    },
    {
      "id": 37031400,
      "category": "Attraction",
      "final_score": 0.3353780181877992
    },
    {
      "id": 13345873,
      "category": "Attraction",
      "final_score": 0.33423786836054264
    },
    {
      "id": 13490946,
      "category": "Attraction",
      "final_score": 0.3325333401605977
    },
    {
      "id": 1940124735,
      "category": "Attraction",
      "final_score": 0.3315101775751308
    },
    {
      "id": 15699373,
      "category": "Attraction",
      "final_score": 0.32338689598901715
    },
    {
      "id": 20066249,
      "category": "Attraction",
      "final_score": 0.321097566074575
    },
    {
      "id": 2145408639,
      "category": "Attraction",
      "final_score": 0.3189276374312465
    },
    {
      "id": 37869673,
      "category": "Attraction",
      "final_score": 0.31872433848405046
    },
    {
      "id": 1109407473,
      "category": "Attraction",
      "final_score": 0.31822158023399255
    },
    {
      "id": 269545324,
      "category": "Attraction",
      "final_score": 0.31769805478497315
    },
    {
      "id": 1775014582,
      "category": "Attraction",
      "final_score": 0.31435944294309937
    },
    {
      "id": 13491150,
      "category": "Attraction",
      "final_score": 0.31223511508748697
    },
    {
      "id": 21824426,
      "category": "Attraction",
      "final_score": 0.3120103191569376
    },
    {
      "id": 1249952785,
      "category": "Attraction",
      "final_score": 0.3118371765095581
    },
    {
      "id": 13345877,
      "category": "Attraction",
      "final_score": 0.3065994782575901
    },
    {
      "id": 11491009,
      "category": "Attraction",
      "final_score": 0.29758155045635787
    },
    {
      "id": 37090227,
      "category": "Attraction",
      "final_score": 0.2968662865746958
    },
    {
      "id": 15685783,
      "category": "Attraction",
      "final_score": 0.28985890015818216
    },
    {
      "id": 266717564,
      "category": "Attraction",
      "final_score": 0.2887896170058541
    },
    {
      "id": 12079976,
      "category": "Attraction",
      "final_score": 0.2887810292034187
    },
    {
      "id": 11620702,
      "category": "Attraction",
      "final_score": 0.2882482397358134
    },
    {
      "id": 12762639,
      "category": "Attraction",
      "final_score": 0.2872964676273297
    },
    {
      "id": 15693581,
      "category": "Attraction",
      "final_score": 0.2862524071927575
    },
    {
      "id": 31506191,
      "category": "Attraction",
      "final_score": 0.2854158596816205
    },
    {
      "id": 939463951,
      "category": "Attraction",
      "final_score": 0.2812219053981053
    },
    {
      "id": 13491657,
      "category": "Attraction",
      "final_score": 0.27470237989827073
    },
    {
      "id": 13313746,
      "category": "Attraction",
      "final_score": 0.268674901691083
    },
    {
      "id": 15371716,
      "category": "Attraction",
      "final_score": 0.2631331912920762
    },
    {
      "id": 20947876,
      "category": "Attraction",
      "final_score": 0.2599458263506081
    },
    {
      "id": 1090555407,
      "category": "Attraction",
      "final_score": 0.25972136098629206
    },
    {
      "id": 11491778,
      "category": "Attraction",
      "final_score": 0.2543680370438155
    },
    {
      "id": 1117620826,
      "category": "Attraction",
      "final_score": 0.2541839514581841
    },
    {
      "id": 1206536601,
      "category": "Attraction",
      "final_score": 0.2520288627941445
    },
    {
      "id": 1412053208,
      "category": "Attraction",
      "final_score": 0.24575107033955726
    },
    {
      "id": 1130774967,
      "category": "Attraction",
      "final_score": 0.24567150360706294
    },
    {
      "id": 13491268,
      "category": "Attraction",
      "final_score": 0.24553001468903496
    },
    {
      "id": 13491444,
      "category": "Attraction",
      "final_score": 0.24506265660956666
    },
    {
      "id": 13491315,
      "category": "Attraction",
      "final_score": 0.24461457692404906
    },
    {
      "id": 13491470,
      "category": "Attraction",
      "final_score": 0.24291567479953632
    },
    {
      "id": 1884028346,
      "category": "Attraction",
      "final_score": 0.23927959172921268
    },
    {
      "id": 1112785467,
      "category": "Attraction",
      "final_score": 0.23890761584074213
    },
    {
      "id": 35188457,
      "category": "Attraction",
      "final_score": 0.23466751771621566
    },
    {
      "id": 13444970,
      "category": "Attraction",
      "final_score": 0.23230174505927845
    },
    {
      "id": 1261782152,
      "category": "Attraction",
      "final_score": 0.22494673635733575
    },
    {
      "id": 15701732,
      "category": "Attraction",
      "final_score": 0.22205437043030463
    },
    {
      "id": 13491186,
      "category": "Attraction",
      "final_score": 0.22192163702352416
    },
    {
      "id": 13300191,
      "category": "Attraction",
      "final_score": 0.21947684466120185
    },
    {
      "id": 32268465,
      "category": "Attraction",
      "final_score": 0.21927776404432886
    },
    {
      "id": 20059236,
      "category": "Attraction",
      "final_score": 0.21589610472141849
    },
    {
      "id": 12955259,
      "category": "Attraction",
      "final_score": 0.21549019837264044
    },
    {
      "id": 2062786512,
      "category": "Attraction",
      "final_score": 0.21448880422156705
    },
    {
      "id": 12390002,
      "category": "Attraction",
      "final_score": 0.21223095926144808
    },
    {
      "id": 15704900,
      "category": "Attraction",
      "final_score": 0.21113825145944173
    },
    {
      "id": 1550291849,
      "category": "Attraction",
      "final_score": 0.2108249367500049
    },
    {
      "id": 1287320440,
      "category": "Attraction",
      "final_score": 0.21043050664328064
    },
    {
      "id": 13491923,
      "category": "Attraction",
      "final_score": 0.2094262437783845
    },
    {
      "id": 20103328,
      "category": "Attraction",
      "final_score": 0.20915816314451804
    },
    {
      "id": 19564244,
      "category": "Attraction",
      "final_score": 0.20905963102804115
    },
    {
      "id": 35372537,
      "category": "Attraction",
      "final_score": 0.20851055089119086
    },
    {
      "id": 1243747688,
      "category": "Attraction",
      "final_score": 0.20826350693915902
    },
    {
      "id": 749351147,
      "category": "Attraction",
      "final_score": 0.20355158658376304
    },
    {
      "id": 11626644,
      "category": "Attraction",
      "final_score": 0.20202405365782172
    },
    {
      "id": 13444336,
      "category": "Attraction",
      "final_score": 0.2007952749660369
    },
    {
      "id": 20054445,
      "category": "Attraction",
      "final_score": 0.20014512528211786
    },
    {
      "id": 19501415,
      "category": "Attraction",
      "final_score": 0.19790857366871406
    },
    {
      "id": 474291808,
      "category": "Attraction",
      "final_score": 0.1970361468733518
    },
    {
      "id": 11687693,
      "category": "Attraction",
      "final_score": 0.19406066915929912
    },
    {
      "id": 15698326,
      "category": "Attraction",
      "final_score": 0.19002363739858885
    },
    {
      "id": 472414455,
      "category": "Attraction",
      "final_score": 0.18487859176293622
    },
    {
      "id": 1346656418,
      "category": "Attraction",
      "final_score": 0.18321905063927327
    },
    {
      "id": 32777223,
      "category": "Attraction",
      "final_score": 0.18316451512958612
    },
    {
      "id": 20066218,
      "category": "Attraction",
      "final_score": 0.16904593162295775
    },
    {
      "id": 1600054868,
      "category": "Attraction",
      "final_score": 0.1653927536172148
    },
    {
      "id": 13491183,
      "category": "Attraction",
      "final_score": 0.1647310540069823
    },
    {
      "id": 13351605,
      "category": "Attraction",
      "final_score": 0.16462259975929563
    },
    {
      "id": 20065935,
      "category": "Attraction",
      "final_score": 0.163927578136429
    },
    {
      "id": 13491884,
      "category": "Attraction",
      "final_score": 0.16297899590303613
    },
    {
      "id": 13491109,
      "category": "Attraction",
      "final_score": 0.15500761839561644
    },
    {
      "id": 37434460,
      "category": "Attraction",
      "final_score": 0.15435153645115518
    },
    {
      "id": 15703904,
      "category": "Attraction",
      "final_score": 0.15263962171353512
    },
    {
      "id": 1338629806,
      "category": "Attraction",
      "final_score": 0.1523147937253478
    },
    {
      "id": 1338629806,
      "category": "Attraction",
      "final_score": 0.1523147937253478
    },
    {
      "id": 15692195,
      "category": "Attraction",
      "final_score": 0.14665594320313838
    },
    {
      "id": 34818378,
      "category": "Attraction",
      "final_score": 0.1451516366683996
    },
    {
      "id": 11663849,
      "category": "Attraction",
      "final_score": 0.14397350354964691
    },
    {
      "id": 11535675,
      "category": "Attraction",
      "final_score": 0.14293061490068917
    },
    {
      "id": 1542622512,
      "category": "Attraction",
      "final_score": 0.13973859198214886
    },
    {
      "id": 1154013651,
      "category": "Attraction",
      "final_score": 0.1372848053142641
    },
    {
      "id": 11620713,
      "category": "Attraction",
      "final_score": 0.13642297678524407
    },
    {
      "id": 20054507,
      "category": "Attraction",
      "final_score": 0.13524145601486753
    },
    {
      "id": 1211834959,
      "category": "Attraction",
      "final_score": 0.1297887643968097
    },
    {
      "id": 12409858,
      "category": "Attraction",
      "final_score": 0.12607765024670148
    },
    {
      "id": 31044854,
      "category": "Attraction",
      "final_score": 0.11507962403189272
    },
    {
      "id": 1881857549,
      "category": "Attraction",
      "final_score": 0.11498416409712314
    },
    {
      "id": 1063021154,
      "category": "Attraction",
      "final_score": 0.10937664050504069
    },
    {
      "id": 38623679,
      "category": "Attraction",
      "final_score": 0.10824068272940263
    },
    {
      "id": 15704484,
      "category": "Attraction",
      "final_score": 0.10358941247499594
    },
    {
      "id": 32794988,
      "category": "Attraction",
      "final_score": 0.10272058177718432
    },
    {
      "id": 19832807,
      "category": "Attraction",
      "final_score": 0.09138142360088564
    },
    {
      "id": 37081677,
      "category": "Attraction",
      "final_score": 0.08312326790836157
    },
    {
      "id": 15703402,
      "category": "Attraction",
      "final_score": 0.06328211536181426
    },
    {
      "id": 15700020,
      "category": "Attraction",
      "final_score": 0.060144344596314965
    },
    {
      "id": 15707029,
      "category": "Attraction",
      "final_score": 0.05854402403085601
    },
    {
      "id": 13491494,
      "category": "Attraction",
      "final_score": 0.05744500005848447
    },
    {
      "id": 13126966,
      "category": "Attraction",
      "final_score": 0.047182949102705894
    },
    {
      "id": 19748069,
      "category": "Attraction",
      "final_score": -0.05225987605626753
    },
    {
      "id": 13345874,
      "category": "Attraction",
      "final_score": -0.13640666166061607
    }
  ]
}